dmf_control_board/dmf_control_board_base.pyd
dmf_control_board/libboost_python-mgw44-mt-1_46_1.dll
dmf_control_board/mingwm10.dll
dmf_control_board/__init__.py
dmf_control_board/driver/arduino.cat
dmf_control_board/driver/arduino.inf
dmf_control_board/firmware/1_0/dmf_control_board.hex
dmf_control_board/firmware/1_1/dmf_control_board.hex
dmf_control_board/firmware/1_2/dmf_control_board.hex
dmf_control_board/firmware/1_3/dmf_control_board.hex
dmf_control_board/firmware/2_0/dmf_control_board.hex
dmf_control_board/firmware/mega2560/1_0/dmf_control_board.hex
dmf_control_board/firmware/mega2560/1_1/dmf_control_board.hex
dmf_control_board/firmware/mega2560/1_2/dmf_control_board.hex
dmf_control_board/firmware/mega2560/1_3/dmf_control_board.hex
dmf_control_board/firmware/mega2560/2_0/dmf_control_board.hex
dmf_control_board/src/dmf_control_board/boost-build.jam
dmf_control_board/src/dmf_control_board/Config.h
dmf_control_board/src/dmf_control_board/Config.h.skeleton
dmf_control_board/src/dmf_control_board/Deserialize.h
dmf_control_board/src/dmf_control_board/DMFControlBoard.cpp
dmf_control_board/src/dmf_control_board/DMFControlBoard.h
dmf_control_board/src/dmf_control_board/dmf_control_board.ino
dmf_control_board/src/dmf_control_board/doxy.cfg
dmf_control_board/src/dmf_control_board/Jamroot
dmf_control_board/src/dmf_control_board/Logging.cpp
dmf_control_board/src/dmf_control_board/Logging.h
dmf_control_board/src/dmf_control_board/Memory.h
dmf_control_board/src/dmf_control_board/PythonWrappers.cpp
dmf_control_board/src/dmf_control_board/RemoteObject.cpp
dmf_control_board/src/dmf_control_board/RemoteObject.h
dmf_control_board/src/dmf_control_board/SConscript.arduino
dmf_control_board/src/dmf_control_board/SConscript.docs
dmf_control_board/src/dmf_control_board/SConscript.host
dmf_control_board/src/dmf_control_board/SimpleSerial.cpp
dmf_control_board/src/dmf_control_board/SimpleSerial.h
wheeler.dmf_control_board-0.2.dist-info/DESCRIPTION.rst
wheeler.dmf_control_board-0.2.dist-info/METADATA
wheeler.dmf_control_board-0.2.dist-info/metadata.json
wheeler.dmf_control_board-0.2.dist-info/RECORD
wheeler.dmf_control_board-0.2.dist-info/top_level.txt
wheeler.dmf_control_board-0.2.dist-info/WHEEL
