Metadata-Version: 2.0
Name: wheeler.dmf-control-board
Version: 0.2
Summary: Arduino-based dmf_control_board firmware and Python API.
Home-page: http://microfluidics.utoronto.ca/git/dmf_control_board.git
Author: Ryan Fobel
Author-email: ryan@fobel.net
License: GPLv2
Platform: UNKNOWN
Requires-Dist: avr-helpers
Requires-Dist: arduino-helpers
Requires-Dist: decorator
